{
  "creator": 1,
  "name": "",
  "description": "",
  "imageVersion": 1,
  "image": "",
  "managers": [
    1
  ],
  "managersCanBeAddedOrRemoved": true,
  "managersCanTransferMoneyWithoutARequest": true,
  "requestsCanBeCreated": true,
  "onlyManagersCanCreateARequest": false,
  "onlyContributorsCanApproveARequest": false,
  "minimumContributionPercentageRequired": 5,
  "minimumApprovalsPercentageRequired": 50,
  "history": "",
  "risks": "",
  "rewards": "",
  "contributions": [
    {
      "contributor": 1,
      "value": 100
    }
  ],
  "transfers": [
    {
      "sender": 1,
      "to": 1,
      "value": 100
    }
  ],
  "requests": [
    {
      "description": "",
      "petitioner": 1,
      "recipient": 1,
      "valueToTransfer": 100,
      "approvers": [
        1
      ],
      "finalize": false
    }
  ]
}